CHANGES.txt
LICENSE.txt
MANIFEST.in
README.md
setup.py
classproperties/__init__.py
classproperties.egg-info/PKG-INFO
classproperties.egg-info/SOURCES.txt
classproperties.egg-info/dependency_links.txt
classproperties.egg-info/top_level.txt