Metadata-Version: 1.1
Name: classproperties
Version: 0.1.3
Summary: property for class methods
Home-page: https://github.com/dpep/pyclassproperties
Author: Daniel Pepper
Author-email: UNKNOWN
License: MIT
Platform: any
Classifier: License :: OSI Approved :: MIT License
Classifier: Development Status :: 2 - Pre-Alpha
Classifier: Programming Language :: Python
Classifier: Topic :: Utilities
Classifier: Topic :: Software Development :: Libraries :: Python Modules
Classifier: Operating System :: OS Independent
Classifier: Natural Language :: English
